Workbook

Sheet Read Me
A1: ShowUp — Spreadsheets to Maintain
A2: Five tabs, one Google Sheet — cleaner for two people to share. Each tab answers a different question you'll actually get asked.
A4: 1. Expenses
A5: Answers: Where has our money gone, and who personally put in what.
A6: Category = Fixed cost / Growth spend / Buffer.
A8: 2. API & Infra Costs
A9: Answers: How much are we actually spending to run this, and are we near any free-tier ceiling.
A10: Check "Within Free Tier?" weekly, not just monthly — it's the column that warns you before an unexpected bill.
A12: 3. Users & Customers
A13: Answers: Who's using this, are they paying, are they active.
A14: User ID is the main reference (e.g. U001), not the raw phone number. If you need phone numbers for ops, keep them in a separate column and use Data > Protected sheets and ranges in Google Sheets to restrict who can see it — health/fitness data plus a phone number in one open sheet is exactly the kind of thing to keep tightly held.
A16: 4. Revenue
... A28: • Only the Monthly Summary needs a fixed cadence — same day each month, no excuses, even if the numbers are small.

Sheet 1. Expenses
A1: Date | B1: Description | C1: Category | D1: Amount Out (₹) | E1: Paid By | F1: Aarya's Contribution (₹) | G1: Tharun's Contribution (₹) | H1: Running Total - Aarya (₹) | I1: Running Total - Tharun (₹) | J1: Notes
H2: =SUM($F$2:F2) | I2: =SUM($G$2:G2)
H3: =SUM($F$2:F3) | I3: =SUM($G$2:G3)
H4: =SUM($F$2:F4) | I4: =SUM($G$2:G4)
H5: =SUM($F$2:F5) | I5: =SUM($G$2:G5)
H6: =SUM($F$2:F6) | I6: =SUM($G$2:G6)
H7: =SUM($F$2:F7) | I7: =SUM($G$2:G7)
H8: =SUM($F$2:F8) | I8: =SUM($G$2:G8)
H9: =SUM($F$2:F9) | I9: =SUM($G$2:G9)
H10: =SUM($F$2:F10) | I10: =SUM($G$2:G10)
H11: =SUM($F$2:F11) | I11: =SUM($G$2:G11)
H12: =SUM($F$2:F12) | I12: =SUM($G$2:G12)
H13: =SUM($F$2:F13) | I13: =SUM($G$2:G13)
... H61: =SUM($F$2:F61) | I61: =SUM($G$2:G61)

Sheet 2. API & Infra Costs
A1: Date | B1: Provider | C1: Usage Type | D1: Quantity | E1: Unit Cost (₹) | F1: Total Cost (₹) | G1: Within Free Tier? | H1: Cumulative Monthly Cost (₹) | I1: Notes
F2: =IF(OR(D2="",E2=""),"",D2*E2) | H2: =IF(A2="","",SUMIFS($F$2:F2,$A$2:A2,">="&EOMONTH(A2,-1)+1))
F3: =IF(OR(D3="",E3=""),"",D3*E3) | H3: =IF(A3="","",SUMIFS($F$2:F3,$A$2:A3,">="&EOMONTH(A3,-1)+1))
F4: =IF(OR(D4="",E4=""),"",D4*E4) | H4: =IF(A4="","",SUMIFS($F$2:F4,$A$2:A4,">="&EOMONTH(A4,-1)+1))
F5: =IF(OR(D5="",E5=""),"",D5*E5) | H5: =IF(A5="","",SUMIFS($F$2:F5,$A$2:A5,">="&EOMONTH(A5,-1)+1))
F6: =IF(OR(D6="",E6=""),"",D6*E6) | H6: =IF(A6="","",SUMIFS($F$2:F6,$A$2:A6,">="&EOMONTH(A6,-1)+1))
F7: =IF(OR(D7="",E7=""),"",D7*E7) | H7: =IF(A7="","",SUMIFS($F$2:F7,$A$2:A7,">="&EOMONTH(A7,-1)+1))
F8: =IF(OR(D8="",E8=""),"",D8*E8) | H8: =IF(A8="","",SUMIFS($F$2:F8,$A$2:A8,">="&EOMONTH(A8,-1)+1))
F9: =IF(OR(D9="",E9=""),"",D9*E9) | H9: =IF(A9="","",SUMIFS($F$2:F9,$A$2:A9,">="&EOMONTH(A9,-1)+1))
F10: =IF(OR(D10="",E10=""),"",D10*E10) | H10: =IF(A10="","",SUMIFS($F$2:F10,$A$2:A10,">="&EOMONTH(A10,-1)+1))
F11: =IF(OR(D11="",E11=""),"",D11*E11) | H11: =IF(A11="","",SUMIFS($F$2:F11,$A$2:A11,">="&EOMONTH(A11,-1)+1))
F12: =IF(OR(D12="",E12=""),"",D12*E12) | H12: =IF(A12="","",SUMIFS($F$2:F12,$A$2:A12,">="&EOMONTH(A12,-1)+1))
F13: =IF(OR(D13="",E13=""),"",D13*E13) | H13: =IF(A13="","",SUMIFS($F$2:F13,$A$2:A13,">="&EOMONTH(A13,-1)+1))
... F61: =IF(OR(D61="",E61=""),"",D61*E61) | H61: =IF(A61="","",SUMIFS($F$2:F61,$A$2:A61,">="&EOMONTH(A61,-1)+1))

Sheet 3. Users & Customers
A1: User ID | B1: Name | C1: Signup Date | D1: Plan | E1: Deposit Paid | F1: Status | G1: Current Streak | H1: Last Check-in | I1: Payment Status | J1: Notes

Sheet 4. Revenue
A1: Date | B1: User ID | C1: Type | D1: Amount (₹) | E1: Payment Method | F1: Notes

Sheet 5. Monthly Summary
A1: Month | B1: Total Revenue (₹) | C1: Total Expenses (₹) | D1: Net Cash Position (₹) | E1: Active Users (start) | F1: New Users | G1: Churned Users | H1: Active Users (end) | I1: MRR (₹) | J1: Notes
B2: =IF(A2="","",SUMIFS('4. Revenue'!$D:$D,'4. Revenue'!$A:$A,">="&A2,'4. Revenue'!$A:$A,"<"&EDATE(A2,1))) | C2: =IF(A2="","",SUMIFS('1. Expenses'!$D:$D,'1. Expenses'!$A:$A,">="&A2,'1. Expenses'!$A:$A,"<"&EDATE(A2,1))+SUMIFS('2. API & Infra Costs'!$F:$F,'2. API & Infra Costs'!$A:$A,">="&A2,'2. API & Infra Costs'!$A:$A,"<"&EDATE(A2,1))) | D2: =IF(A2="","",B2-C2) | H2: =IF(A2="","",E2+F2-G2) | I2: =IF(A2="","",SUMIFS('4. Revenue'!$D:$D,'4. Revenue'!$A:$A,">="&A2,'4. Revenue'!$A:$A,"<"&EDATE(A2,1),'4. Revenue'!$C:$C,"Monthly Subscription"))
B3: =IF(A3="","",SUMIFS('4. Revenue'!$D:$D,'4. Revenue'!$A:$A,">="&A3,'4. Revenue'!$A:$A,"<"&EDATE(A3,1))) | C3: =IF(A3="","",SUMIFS('1. Expenses'!$D:$D,'1. Expenses'!$A:$A,">="&A3,'1. Expenses'!$A:$A,"<"&EDATE(A3,1))+SUMIFS('2. API & Infra Costs'!$F:$F,'2. API & Infra Costs'!$A:$A,">="&A3,'2. API & Infra Costs'!$A:$A,"<"&EDATE(A3,1))) | D3: =IF(A3="","",B3-C3) | H3: =IF(A3="","",E3+F3-G3) | I3: =IF(A3="","",SUMIFS('4. Revenue'!$D:$D,'4. Revenue'!$A:$A,">="&A3,'4. Revenue'!$A:$A,"<"&EDATE(A3,1),'4. Revenue'!$C:$C,"Monthly Subscription"))
B4: =IF(A4="","",SUMIFS('4. Revenue'!$D:$D,'4. Revenue'!$A:$A,">="&A4,'4. Revenue'!$A:$A,"<"&EDATE(A4,1))) | C4: =IF(A4="","",SUMIFS('1. Expenses'!$D:$D,'1. Expenses'!$A:$A,">="&A4,'1. Expenses'!$A:$A,"<"&EDATE(A4,1))+SUMIFS('2. API & Infra Costs'!$F:$F,'2. API & Infra Costs'!$A:$A,">="&A4,'2. API & Infra Costs'!$A:$A,"<"&EDATE(A4,1))) | D4: =IF(A4="","",B4-C4) | H4: =IF(A4="","",E4+F4-G4) | I4: =IF(A4="","",SUMIFS('4. Revenue'!$D:$D,'4. Revenue'!$A:$A,">="&A4,'4. Revenue'!$A:$A,"<"&EDATE(A4,1),'4. Revenue'!$C:$C,"Monthly Subscription"))
B5: =IF(A5="","",SUMIFS('4. Revenue'!$D:$D,'4. Revenue'!$A:$A,">="&A5,'4. Revenue'!$A:$A,"<"&EDATE(A5,1))) | C5: =IF(A5="","",SUMIFS('1. Expenses'!$D:$D,'1. Expenses'!$A:$A,">="&A5,'1. Expenses'!$A:$A,"<"&EDATE(A5,1))+SUMIFS('2. API & Infra Costs'!$F:$F,'2. API & Infra Costs'!$A:$A,">="&A5,'2. API & Infra Costs'!$A:$A,"<"&EDATE(A5,1))) | D5: =IF(A5="","",B5-C5) | H5: =IF(A5="","",E5+F5-G5) | I5: =IF(A5="","",SUMIFS('4. Revenue'!$D:$D,'4. Revenue'!$A:$A,">="&A5,'4. Revenue'!$A:$A,"<"&EDATE(A5,1),'4. Revenue'!$C:$C,"Monthly Subscription"))
B6: =IF(A6="","",SUMIFS('4. Revenue'!$D:$D,'4. Revenue'!$A:$A,">="&A6,'4. Revenue'!$A:$A,"<"&EDATE(A6,1))) | C6: =IF(A6="","",SUMIFS('1. Expenses'!$D:$D,'1. Expenses'!$A:$A,">="&A6,'1. Expenses'!$A:$A,"<"&EDATE(A6,1))+SUMIFS('2. API & Infra Costs'!$F:$F,'2. API & Infra Costs'!$A:$A,">="&A6,'2. API & Infra Costs'!$A:$A,"<"&EDATE(A6,1))) | D6: =IF(A6="","",B6-C6) | H6: =IF(A6="","",E6+F6-G6) | I6: =IF(A6="","",SUMIFS('4. Revenue'!$D:$D,'4. Revenue'!$A:$A,">="&A6,'4. Revenue'!$A:$A,"<"&EDATE(A6,1),'4. Revenue'!$C:$C,"Monthly Subscription"))
B7: =IF(A7="","",SUMIFS('4. Revenue'!$D:$D,'4. Revenue'!$A:$A,">="&A7,'4. Revenue'!$A:$A,"<"&EDATE(A7,1))) | C7: =IF(A7="","",SUMIFS('1. Expenses'!$D:$D,'1. Expenses'!$A:$A,">="&A7,'1. Expenses'!$A:$A,"<"&EDATE(A7,1))+SUMIFS('2. API & Infra Costs'!$F:$F,'2. API & Infra Costs'!$A:$A,">="&A7,'2. API & Infra Costs'!$A:$A,"<"&EDATE(A7,1))) | D7: =IF(A7="","",B7-C7) | H7: =IF(A7="","",E7+F7-G7) | I7: =IF(A7="","",SUMIFS('4. Revenue'!$D:$D,'4. Revenue'!$A:$A,">="&A7,'4. Revenue'!$A:$A,"<"&EDATE(A7,1),'4. Revenue'!$C:$C,"Monthly Subscription"))
B8: =IF(A8="","",SUMIFS('4. Revenue'!$D:$D,'4. Revenue'!$A:$A,">="&A8,'4. Revenue'!$A:$A,"<"&EDATE(A8,1))) | C8: =IF(A8="","",SUMIFS('1. Expenses'!$D:$D,'1. Expenses'!$A:$A,">="&A8,'1. Expenses'!$A:$A,"<"&EDATE(A8,1))+SUMIFS('2. API & Infra Costs'!$F:$F,'2. API & Infra Costs'!$A:$A,">="&A8,'2. API & Infra Costs'!$A:$A,"<"&EDATE(A8,1))) | D8: =IF(A8="","",B8-C8) | H8: =IF(A8="","",E8+F8-G8) | I8: =IF(A8="","",SUMIFS('4. Revenue'!$D:$D,'4. Revenue'!$A:$A,">="&A8,'4. Revenue'!$A:$A,"<"&EDATE(A8,1),'4. Revenue'!$C:$C,"Monthly Subscription"))
B9: =IF(A9="","",SUMIFS('4. Revenue'!$D:$D,'4. Revenue'!$A:$A,">="&A9,'4. Revenue'!$A:$A,"<"&EDATE(A9,1))) | C9: =IF(A9="","",SUMIFS('1. Expenses'!$D:$D,'1. Expenses'!$A:$A,">="&A9,'1. Expenses'!$A:$A,"<"&EDATE(A9,1))+SUMIFS('2. API & Infra Costs'!$F:$F,'2. API & Infra Costs'!$A:$A,">="&A9,'2. API & Infra Costs'!$A:$A,"<"&EDATE(A9,1))) | D9: =IF(A9="","",B9-C9) | H9: =IF(A9="","",E9+F9-G9) | I9: =IF(A9="","",SUMIFS('4. Revenue'!$D:$D,'4. Revenue'!$A:$A,">="&A9,'4. Revenue'!$A:$A,"<"&EDATE(A9,1),'4. Revenue'!$C:$C,"Monthly Subscription"))
B10: =IF(A10="","",SUMIFS('4. Revenue'!$D:$D,'4. Revenue'!$A:$A,">="&A10,'4. Revenue'!$A:$A,"<"&EDATE(A10,1))) | C10: =IF(A10="","",SUMIFS('1. Expenses'!$D:$D,'1. Expenses'!$A:$A,">="&A10,'1. Expenses'!$A:$A,"<"&EDATE(A10,1))+SUMIFS('2. API & Infra Costs'!$F:$F,'2. API & Infra Costs'!$A:$A,">="&A10,'2. API & Infra Costs'!$A:$A,"<"&EDATE(A10,1))) | D10: =IF(A10="","",B10-C10) | H10: =IF(A10="","",E10+F10-G10) | I10: =IF(A10="","",SUMIFS('4. Revenue'!$D:$D,'4. Revenue'!$A:$A,">="&A10,'4. Revenue'!$A:$A,"<"&EDATE(A10,1),'4. Revenue'!$C:$C,"Monthly Subscription"))
B11: =IF(A11="","",SUMIFS('4. Revenue'!$D:$D,'4. Revenue'!$A:$A,">="&A11,'4. Revenue'!$A:$A,"<"&EDATE(A11,1))) | C11: =IF(A11="","",SUMIFS('1. Expenses'!$D:$D,'1. Expenses'!$A:$A,">="&A11,'1. Expenses'!$A:$A,"<"&EDATE(A11,1))+SUMIFS('2. API & Infra Costs'!$F:$F,'2. API & Infra Costs'!$A:$A,">="&A11,'2. API & Infra Costs'!$A:$A,"<"&EDATE(A11,1))) | D11: =IF(A11="","",B11-C11) | H11: =IF(A11="","",E11+F11-G11) | I11: =IF(A11="","",SUMIFS('4. Revenue'!$D:$D,'4. Revenue'!$A:$A,">="&A11,'4. Revenue'!$A:$A,"<"&EDATE(A11,1),'4. Revenue'!$C:$C,"Monthly Subscription"))
B12: =IF(A12="","",SUMIFS('4. Revenue'!$D:$D,'4. Revenue'!$A:$A,">="&A12,'4. Revenue'!$A:$A,"<"&EDATE(A12,1))) | C12: =IF(A12="","",SUMIFS('1. Expenses'!$D:$D,'1. Expenses'!$A:$A,">="&A12,'1. Expenses'!$A:$A,"<"&EDATE(A12,1))+SUMIFS('2. API & Infra Costs'!$F:$F,'2. API & Infra Costs'!$A:$A,">="&A12,'2. API & Infra Costs'!$A:$A,"<"&EDATE(A12,1))) | D12: =IF(A12="","",B12-C12) | H12: =IF(A12="","",E12+F12-G12) | I12: =IF(A12="","",SUMIFS('4. Revenue'!$D:$D,'4. Revenue'!$A:$A,">="&A12,'4. Revenue'!$A:$A,"<"&EDATE(A12,1),'4. Revenue'!$C:$C,"Monthly Subscription"))
B13: =IF(A13="","",SUMIFS('4. Revenue'!$D:$D,'4. Revenue'!$A:$A,">="&A13,'4. Revenue'!$A:$A,"<"&EDATE(A13,1))) | C13: =IF(A13="","",SUMIFS('1. Expenses'!$D:$D,'1. Expenses'!$A:$A,">="&A13,'1. Expenses'!$A:$A,"<"&EDATE(A13,1))+SUMIFS('2. API & Infra Costs'!$F:$F,'2. API & Infra Costs'!$A:$A,">="&A13,'2. API & Infra Costs'!$A:$A,"<"&EDATE(A13,1))) | D13: =IF(A13="","",B13-C13) | H13: =IF(A13="","",E13+F13-G13) | I13: =IF(A13="","",SUMIFS('4. Revenue'!$D:$D,'4. Revenue'!$A:$A,">="&A13,'4. Revenue'!$A:$A,"<"&EDATE(A13,1),'4. Revenue'!$C:$C,"Monthly Subscription"))
... B37: =IF(A37="","",SUMIFS('4. Revenue'!$D:$D,'4. Revenue'!$A:$A,">="&A37,'4. Revenue'!$A:$A,"<"&EDATE(A37,1))) | C37: =IF(A37="","",SUMIFS('1. Expenses'!$D:$D,'1. Expenses'!$A:$A,">="&A37,'1. Expenses'!$A:$A,"<"&EDATE(A37,1))+SUMIFS('2. API & Infra Costs'!$F:$F,'2. API & Infra Costs'!$A:$A,">="&A37,'2. API & Infra Costs'!$A:$A,"<"&EDATE(A37,1))) | D37: =IF(A37="","",B37-C37) | H37: =IF(A37="","",E37+F37-G37) | I37: =IF(A37="","",SUMIFS('4. Revenue'!$D:$D,'4. Revenue'!$A:$A,">="&A37,'4. Revenue'!$A:$A,"<"&EDATE(A37,1),'4. Revenue'!$C:$C,"Monthly Subscription"))
